{
  "name": "Neuro On-Call Quick References",
  "slug": "neuro-on-call",
  "icon": "🚨",
  "color": "bg-rose-100 text-rose-800 border-rose-200",
  "toc": [
    {
      "level": 1,
      "text": "Seizure Medications & Dosing",
      "id": "seizure-medications"
    },
    {
      "level": 2,
      "text": "ASM On-Call Dosing",
      "id": "seizure-medications"
    },
    {
      "level": 2,
      "text": "Diastat (Rectal Diazepam)",
      "id": "diastat-dosing"
    },
    {
      "level": 2,
      "text": "Valtoco (Intranasal Diazepam)",
      "id": "valtoco-dosing"
    },
    {
      "level": 2,
      "text": "Benzodiazepines – Quick Reference",
      "id": "benzo-quick-reference"
    },
    {
      "level": 1,
      "text": "Benzodiazepine Equivalency",
      "id": "benzo-equivalency"
    },
    {
      "level": 1,
      "text": "Febrile Seizure On-Call",
      "id": "febrile-seizures"
    },
    {
      "level": 1,
      "text": "Acute Pathways",
      "id": "acute-pathways"
    },
    {
      "level": 1,
      "text": "On Call Resources",
      "id": "on-call-resources"
    },
    {
      "level": 2,
      "text": "Faculty Call Schedule",
      "id": "faculty-call-schedule"
    }
  ],
  "html": "<section aria-label=\"Seizure Medications &amp; Dosing\">\n<div style=\"display:flex;align-items:flex-start;gap:0.875rem;background:#f5f3ff;border-left:4px solid #7c3aed;border-radius:0 10px 10px 0;padding:1rem 1.25rem 1rem 1.25rem;margin:2.5rem 0 1.25rem;\">\n  <span style=\"font-size:1.75rem;line-height:1;flex-shrink:0;margin-top:0.1rem;\" aria-hidden=\"true\">💊</span>\n  <div style=\"flex:1;min-width:0;\">\n    <h2 id=\"seizure-medications\" style=\"margin:0 0 0.25rem;padding:0;font-size:1.1rem;font-weight:700;color:#7c3aed;border:none;background:none;\">Seizure Medications &amp; Dosing</h2>\n    <p style=\"margin:0;font-size:0.75rem;color:#7c3aed;opacity:0.85;\">Benzodiazepine dosing and weight-based reference guides</p>\n  </div>\n</div>\n<div class=\"table-wrap\"><table>\n<thead><tr>\n<th>Drug</th>\n<th>Initial dose</th>\n<th>Target dose</th>\n<th>Blood conc. (µg/mL)</th>\n<th>Half‑life (h)</th>\n<th>Major contraindications / cautions</th>\n</tr></thead>\n<tbody>\n<tr><td><strong>Brivaracetam</strong></td><td>1–2 mg/kg/day</td><td>2–4 mg/kg/day</td><td>2–10</td><td>7–8</td><td>Prior serious hypersensitivity to levetiracetam/brivaracetam; significant hepatic impairment (adjust dose)</td></tr>\n<tr><td><strong>Cannabidiol (Epidiolex)</strong></td><td>5 mg/kg/day</td><td>10–20 mg/kg/day divided BID</td><td>†</td><td>50–60</td><td>Significant hepatic impairment without monitoring; interactions (esp. valproate, clobazam); monitor LFTs</td></tr>\n<tr><td><strong>Cenobamate (Xcopri)</strong></td><td>~0.5–1 mg/kg/day (slow titration)</td><td>3–5 mg/kg/day (max ~200 mg/day in adolescents)</td><td>†</td><td>50–60</td><td>Familial short‑QT syndrome, DRESS with rapid titration, significant hepatic impairment</td></tr>\n<tr><td><strong>Clobazam</strong></td><td>0.1–0.2 mg/kg/day</td><td>0.3–1 mg/kg/day</td><td>†</td><td>18–50</td><td>Severe hepatic impairment, significant respiratory depression, other sedatives</td></tr>\n<tr><td><strong>Clonazepam</strong></td><td>0.02 mg/kg/day</td><td>0.5–1 mg/day</td><td>*</td><td>20–40</td><td>Significant respiratory depression, severe liver disease</td></tr>\n<tr><td><strong>Ethosuximide</strong></td><td>10 mg/kg/day</td><td>15–40 mg/kg/day</td><td>50–100</td><td>30–40</td><td>Porphyria, severe hepatic or renal impairment</td></tr>\n<tr><td><strong>Felbamate</strong></td><td>15 mg/kg/day</td><td>15–45 mg/kg/day</td><td>40–80</td><td>20–23</td><td>History of aplastic anemia or hepatic failure</td></tr>\n<tr><td><strong>Fenfluramine</strong></td><td>0.1 mg/kg/day</td><td>0.35–0.7 mg/kg/day (per label max)</td><td>†</td><td>20–30</td><td>Valvular heart disease or pulmonary arterial hypertension; requires echo monitoring</td></tr>\n<tr><td><strong>Fosphenytoin</strong> (IV, as PE)</td><td>5–10 mg/kg/day equivalent</td><td>5–10 mg/kg/day</td><td>10–25</td><td>24</td><td>Sinus bradycardia, SA block, 2nd/3rd‑degree AV block, prior phenytoin hypersensitivity</td></tr>\n<tr><td><strong>Gabapentin</strong></td><td>10–15 mg/kg/day</td><td>30–50 mg/kg/day divided TID</td><td>†</td><td>5–7</td><td>Severe renal impairment without dose adjustment; caution with CNS depressants</td></tr>\n<tr><td><strong>Lacosamide</strong></td><td>2–3 mg/kg/day</td><td>6–12 mg/kg/day</td><td>10–20</td><td>12–16</td><td>2nd/3rd‑degree AV block, significant PR prolongation or conduction disease</td></tr>\n<tr><td><strong>Lamotrigine</strong> (non‑valproate)</td><td>0.5 mg/kg/day</td><td>5–10 mg/kg/day</td><td>2–20</td><td>25 (monotherapy)</td><td>Prior serious rash (SJS/TEN), rapid titration, valproate co‑use without dose adjustment</td></tr>\n<tr><td><strong>Levetiracetam</strong></td><td>30 mg/kg/day</td><td>60 mg/kg/day</td><td>15–40</td><td>5</td><td>Behavioral toxicity; adjust in renal impairment</td></tr>\n<tr><td><strong>Oxcarbazepine</strong></td><td>10 mg/kg/day</td><td>20–40 mg/kg/day</td><td>10–40</td><td>9</td><td>Prior carbamazepine hypersensitivity, HLA‑B*1502 risk, hyponatremia</td></tr>\n<tr><td><strong>Phenobarbital</strong></td><td>3–5 mg/kg/day</td><td>5–10 mg/kg/day</td><td>15–40</td><td>35–73</td><td>Severe respiratory depression, porphyria, advanced hepatic impairment</td></tr>\n<tr><td><strong>Rufinamide</strong></td><td>10 mg/kg/day</td><td>30–45 mg/kg/day divided BID</td><td>5–30</td><td>6–10</td><td>Familial short‑QT syndrome; caution in hepatic impairment and with QT‑affecting drugs</td></tr>\n<tr><td><strong>Stiripentol</strong></td><td>25 mg/kg/day</td><td>50–75 mg/kg/day divided BID–TID</td><td>†</td><td>4–13</td><td>Hepatic/renal impairment; increases clobazam/valproate levels</td></tr>\n<tr><td><strong>Topiramate</strong></td><td>1–3 mg/kg/day</td><td>5–9 mg/kg/day</td><td>†</td><td>18–30</td><td>Kidney stones, metabolic acidosis, glaucoma; adjust in renal impairment</td></tr>\n<tr><td><strong>Valproate</strong></td><td>20 mg/kg/day</td><td>30–60 mg/kg/day</td><td>50–100</td><td>6–15</td><td>Pregnancy, urea‑cycle defects, significant liver disease, POLG‑related disorders</td></tr>\n<tr><td><strong>Vigabatrin</strong></td><td>40–60 mg/kg/day</td><td>60–80 mg/kg/day</td><td>†</td><td>Days</td><td>Pre‑existing serious visual field loss; vision toxicity risk</td></tr>\n<tr><td><strong>Zonisamide</strong></td><td>1.5 mg/kg/day</td><td>6 mg/kg/day</td><td>10–40</td><td>24–60</td><td>Sulfonamide allergy, kidney stones, metabolic acidosis, oligohidrosis/heat‑stroke risk</td></tr>\n</tbody>\n</table></div>\n<p style=\"font-size:0.7rem;color:#64748b;margin-top:0.25rem;\">* No routine therapeutic range. &nbsp; † No well‑established serum therapeutic range; monitoring is clinical.</p>\n\n<h3 id=\"diastat-dosing\">Diastat (Rectal Diazepam) – Children</h3>\n<p>Use age‑based concentration and weight‑based dose (max 20 mg).</p>\n\n<h4 id=\"ages-2-5-years-0-5-mg-kg\">Ages 2–5 years (0.5 mg/kg)</h4>\n<div class=\"table-wrap\"><table>\n<thead><tr><th>Weight (kg)</th><th>Dose (mg)</th></tr></thead>\n<tbody>\n<tr><td>6–10</td><td>5</td></tr>\n<tr><td>11–15</td><td>7.5</td></tr>\n<tr><td>16–20</td><td>10</td></tr>\n<tr><td>21–25</td><td>12.5</td></tr>\n<tr><td>26–30</td><td>15</td></tr>\n<tr><td>31–35</td><td>17.5</td></tr>\n<tr><td>36–44</td><td>20</td></tr>\n</tbody>\n</table></div>\n\n<h4 id=\"ages-6-11-years-0-3-mg-kg\">Ages 6–11 years (0.3 mg/kg)</h4>\n<div class=\"table-wrap\"><table>\n<thead><tr><th>Weight (kg)</th><th>Dose (mg)</th></tr></thead>\n<tbody>\n<tr><td>10–16</td><td>5</td></tr>\n<tr><td>17–25</td><td>7.5</td></tr>\n<tr><td>26–33</td><td>10</td></tr>\n<tr><td>34–41</td><td>12.5</td></tr>\n<tr><td>42–50</td><td>15</td></tr>\n<tr><td>51–58</td><td>17.5</td></tr>\n<tr><td>59–74</td><td>20</td></tr>\n</tbody>\n</table></div>\n\n<h4 id=\"ages-12-years-0-2-mg-kg\">Ages ≥12 years (0.2 mg/kg)</h4>\n<div class=\"table-wrap\"><table>\n<thead><tr><th>Weight (kg)</th><th>Dose (mg)</th></tr></thead>\n<tbody>\n<tr><td>14–25</td><td>5</td></tr>\n<tr><td>26–37</td><td>7.5</td></tr>\n<tr><td>38–50</td><td>10</td></tr>\n<tr><td>51–62</td><td>12.5</td></tr>\n<tr><td>63–75</td><td>15</td></tr>\n<tr><td>76–87</td><td>17.5</td></tr>\n<tr><td>88–111</td><td>20</td></tr>\n</tbody>\n</table></div>\n\n<h3 id=\"valtoco-dosing\">Valtoco (Intranasal Diazepam) – Children ≥6 Years</h3>\n<p>Individualized dosing based on age and weight (max 20 mg per dose).</p>\n\n<h4 id=\"ages-6-11-years-0-3-mg-kg-0-66-mg-lb\">Ages 6–11 years (0.3 mg/kg; 0.66 mg/lb)</h4>\n<div class=\"table-wrap\"><table>\n<thead><tr><th>Weight (kg)</th><th>Dose (mg)</th><th>Given as</th></tr></thead>\n<tbody>\n<tr><td>10–18</td><td>5</td><td>One 5‑mg nasal spray device in one nostril</td></tr>\n<tr><td>19–37</td><td>10</td><td>One 10‑mg nasal spray device in one nostril</td></tr>\n<tr><td>38–55</td><td>15</td><td>Two 7.5‑mg nasal spray devices, one in each nostril</td></tr>\n<tr><td>56–74</td><td>20</td><td>Two 10‑mg nasal spray devices, one in each nostril</td></tr>\n</tbody>\n</table></div>\n\n<h4 id=\"ages-12-years-0-2-mg-kg-0-44-mg-lb\">Ages ≥12 years (0.2 mg/kg; 0.44 mg/lb)</h4>\n<div class=\"table-wrap\"><table>\n<thead><tr><th>Weight (kg)</th><th>Dose (mg)</th><th>Given as</th></tr></thead>\n<tbody>\n<tr><td>14–27</td><td>5</td><td>One 5‑mg nasal spray device in one nostril</td></tr>\n<tr><td>28–50</td><td>10</td><td>One 10‑mg nasal spray device in one nostril</td></tr>\n<tr><td>51–75</td><td>15</td><td>Two 7.5‑mg nasal spray devices, one in each nostril</td></tr>\n<tr><td>≥76</td><td>20</td><td>Two 10‑mg nasal spray devices, one in each nostril</td></tr>\n</tbody>\n</table></div>\n\n\n\n<h3 id=\"benzo-quick-reference\">Benzodiazepines for Seizures – Quick Reference</h3>\n<div class=\"table-wrap\"><table>\n<thead><tr>\n<th>Medication</th>\n<th>Adult dosing</th>\n<th>Pediatric dosing</th>\n<th>Key adverse effects</th>\n</tr></thead>\n<tbody>\n<tr>\n<td><strong>Diazepam</strong> (IV / PR)</td>\n<td>0.15 mg/kg IV (max 10 mg per dose); may redose in 5 min</td>\n<td>PR: 2–5 yrs 0.5 mg/kg; 6–11 yrs 0.3 mg/kg; ≥12 yrs 0.2 mg/kg (see Diastat/Valtoco tables for exact mg)</td>\n<td>Respiratory depression; hypotension and bradycardia (propylene glycol–containing IV)</td>\n</tr>\n<tr>\n<td><strong>Lorazepam</strong> (IV)</td>\n<td>0.1 mg/kg IV (max 4 mg per dose); may redose in 10 min</td>\n<td>0.1 mg/kg IV (max 4 mg per dose); may redose in 10 min</td>\n<td>Respiratory depression; hypotension and bradycardia (propylene glycol–containing IV)</td>\n</tr>\n<tr>\n<td><strong>Midazolam</strong> (IV / IM / IN / buccal)</td>\n<td>0.2 mg/kg IV or IM (max 10 mg); may redose in 10 min</td>\n<td>IM: 10 mg if >40 kg; 5 mg if 13–40 kg. IN: 0.2 mg/kg. Buccal: 0.5 mg/kg</td>\n<td>Respiratory depression; hypotension</td>\n</tr>\n</tbody>\n</table></div>\n\n<figure style=\"margin:1.25rem 0;\">\n  <img src=\"/images/neuro-on-call/the-height-of-man-rule-schematic-diagram-with-regard-to-dosing-of-children-with.png\" alt=\"Weight-Based Dosing Schematic\" style=\"max-width:100%;border-radius:10px;border:1px solid #e2e8f0;box-shadow:0 1px 4px rgba(0,0,0,0.08);display:block;margin:0 auto;\">\n  <figcaption style=\"text-align:center;font-size:0.75rem;color:#64748b;margin-top:0.5rem;font-style:italic;\">Weight-Based Dosing Schematic</figcaption>\n</figure>\n\n</section>\n\n<section aria-label=\"Benzodiazepine Equivalency\">\n<div style=\"display:flex;align-items:flex-start;gap:0.875rem;background:#faf5ff;border-left:4px solid #9333ea;border-radius:0 10px 10px 0;padding:1rem 1.25rem 1rem 1.25rem;margin:2.5rem 0 1.25rem;\">\n  <span style=\"font-size:1.75rem;line-height:1;flex-shrink:0;margin-top:0.1rem;\" aria-hidden=\"true\">⚖️</span>\n  <div style=\"flex:1;min-width:0;\">\n    <h2 id=\"benzo-equivalency\" style=\"margin:0 0 0.25rem;padding:0;font-size:1.1rem;font-weight:700;color:#9333ea;border:none;background:none;\">Benzodiazepine Equivalency Table</h2>\n    <p style=\"margin:0;font-size:0.75rem;color:#9333ea;opacity:0.85;\">Approximate oral dose equivalents and properties</p>\n  </div>\n</div>\n\n<div class=\"table-wrap\"><table>\n<thead><tr>\n<th>Name (generic / brand)</th>\n<th>Approx. dose equivalent to 10 mg diazepam</th>\n<th>Common tablet strengths</th>\n<th>Duration of action*</th>\n<th>Half‑life** (hours)</th>\n</tr></thead>\n<tbody>\n<tr><td><strong>Alprazolam</strong> (Xanax)</td><td>0.5–1 mg</td><td>0.25 mg, 0.5 mg, 1 mg, 2 mg (XR 0.5–3 mg)</td><td>Short</td><td>6–26 (XR ~10–16)</td></tr>\n<tr><td><strong>Clobazam</strong> (Onfi, Sympazan)</td><td>20 mg</td><td>10 mg, 20 mg</td><td>Very long</td><td>&gt;100</td></tr>\n<tr><td><strong>Clonazepam</strong> (Klonopin)</td><td>0.5 mg</td><td>0.125 mg, 0.25 mg (ODT), 0.5 mg, 1 mg, 2 mg</td><td>Long</td><td>18–50</td></tr>\n<tr><td><strong>Diazepam</strong> (Valium)</td><td>10 mg</td><td>2 mg, 5 mg, 10 mg</td><td>Very long</td><td>20–80</td></tr>\n<tr><td><strong>Lorazepam</strong> (Ativan)</td><td>1–2 mg</td><td>0.5 mg, 1 mg, 2 mg</td><td>Intermediate</td><td>10–20</td></tr>\n</tbody>\n</table></div>\n<p style=\"font-size:0.7rem;color:#64748b;margin-top:0.25rem;\">* Very short &lt;6 h, short ~6–12 h, intermediate ~12–24 h, long ~24–48 h, very long &gt;48 h.<br>** Includes active metabolites where relevant.</p>\n\n</section>\n\n<section aria-label=\"Febrile Seizure On-Call References\">\n<div style=\"display:flex;align-items:flex-start;gap:0.875rem;background:#ea580c10;border-left:4px solid #ea580c;border-radius:0 10px 10px 0;padding:1rem 1.25rem 1rem 1.25rem;margin:2.5rem 0 1.25rem;\">\n  <span style=\"font-size:1.75rem;line-height:1;flex-shrink:0;margin-top:0.1rem;\" aria-hidden=\"true\">🌡️</span>\n  <div style=\"flex:1;min-width:0;\">\n    <h2 id=\"febrile-seizures\" style=\"margin:0 0 0.25rem;padding:0;font-size:1.1rem;font-weight:700;color:#ea580c;border:none;background:none;\">Febrile Seizure On-Call References</h2>\n    <p style=\"margin:0;font-size:0.75rem;color:#ea580c;opacity:0.85;\">Quick reference guides for febrile seizure evaluation and management</p>\n  </div>\n</div><figure style=\"margin:1.25rem 0;\">\n  <img src=\"/images/neuro-on-call/img-7642-1-.png\" alt=\"Febrile Seizures — Simple vs Complex Classification & Algorithm\" style=\"max-width:100%;border-radius:10px;border:1px solid #e2e8f0;box-shadow:0 1px 4px rgba(0,0,0,0.08);display:block;margin:0 auto;\">\n  <figcaption style=\"text-align:center;font-size:0.75rem;color:#64748b;margin-top:0.5rem;font-style:italic;\">Febrile Seizures — Simple vs Complex Classification & Complex Febrile Seizure Algorithm</figcaption>\n</figure>\n</section>\n\n\n\n\n\n<section aria-label=\"Acute Pathways\">\n<div style=\"display:flex;align-items:flex-start;gap:0.875rem;background:#fef2f2;border-left:4px solid #dc2626;border-radius:0 10px 10px 0;padding:1rem 1.25rem 1rem 1.25rem;margin:2.5rem 0 1.25rem;\">\n  <span style=\"font-size:1.75rem;line-height:1;flex-shrink:0;margin-top:0.1rem;\" aria-hidden=\"true\">🗺️</span>\n  <div style=\"flex:1;min-width:0;\">\n    <h2 id=\"acute-pathways\" style=\"margin:0 0 0.25rem;padding:0;font-size:1.1rem;font-weight:700;color:#dc2626;border:none;background:none;\">Acute Pathways</h2>\n    <p style=\"margin:0;font-size:0.75rem;color:#dc2626;opacity:0.85;\">NCH clinical pathway documents for acute neurologic emergencies</p>\n  </div>\n</div>\n\n<div style=\"display:grid;grid-template-columns:1fr 1fr;gap:0.75rem;margin:1rem 0;\">\n\n<a href=\"/pathways/#seizure-status\" style=\"display:flex;align-items:center;gap:0.75rem;padding:0.875rem 1rem;border-radius:10px;border:2px solid #dc2626;background:#fef2f2;text-decoration:none;transition:all 0.15s;\">\n  <span style=\"font-size:1.25rem;\">⚡</span>\n  <div>\n    <div style=\"font-weight:700;color:#dc2626;font-size:0.85rem;line-height:1.3;\">Status Epilepticus</div>\n    <div style=\"font-size:0.65rem;color:#991b1b;opacity:0.8;\">SE pathway &amp; refractory SE</div>\n  </div>\n</a>\n\n<a href=\"/pathways/#seizure-status\" style=\"display:flex;align-items:center;gap:0.75rem;padding:0.875rem 1rem;border-radius:10px;border:2px solid #dc2626;background:#fef2f2;text-decoration:none;transition:all 0.15s;\">\n  <span style=\"font-size:1.25rem;\">👶</span>\n  <div>\n    <div style=\"font-weight:700;color:#dc2626;font-size:0.85rem;line-height:1.3;\">Neonatal Seizures</div>\n    <div style=\"font-size:0.65rem;color:#991b1b;opacity:0.8;\">Neonatal seizure pathway</div>\n  </div>\n</a>\n\n<a href=\"/pathways/#stroke-hie\" style=\"display:flex;align-items:center;gap:0.75rem;padding:0.875rem 1rem;border-radius:10px;border:2px solid #dc2626;background:#fef2f2;text-decoration:none;transition:all 0.15s;\">\n  <span style=\"font-size:1.25rem;\">🧠</span>\n  <div>\n    <div style=\"font-weight:700;color:#dc2626;font-size:0.85rem;line-height:1.3;\">Stroke Alert</div>\n    <div style=\"font-size:0.65rem;color:#991b1b;opacity:0.8;\">Stroke &amp; HIE pathways</div>\n  </div>\n</a>\n\n<a href=\"/pathways/#headache-migrainosus\" style=\"display:flex;align-items:center;gap:0.75rem;padding:0.875rem 1rem;border-radius:10px;border:2px solid #dc2626;background:#fef2f2;text-decoration:none;transition:all 0.15s;\">\n  <span style=\"font-size:1.25rem;\">🤕</span>\n  <div>\n    <div style=\"font-weight:700;color:#dc2626;font-size:0.85rem;line-height:1.3;\">Status Migrainosus</div>\n    <div style=\"font-size:0.65rem;color:#991b1b;opacity:0.8;\">Migraine emergency protocol</div>\n  </div>\n</a>\n\n</div>\n</section>\n\n\n\n\n<section aria-label=\"On Call Resources\">\n<div style=\"display:flex;align-items:flex-start;gap:0.875rem;background:#ecfdf5;border-left:4px solid #059669;border-radius:0 10px 10px 0;padding:1rem 1.25rem 1rem 1.25rem;margin:2.5rem 0 1.25rem;\">\n  <span style=\"font-size:1.75rem;line-height:1;flex-shrink:0;margin-top:0.1rem;\" aria-hidden=\"true\">📋</span>\n  <div style=\"flex:1;min-width:0;\">\n    <h2 id=\"on-call-resources\" style=\"margin:0 0 0.25rem;padding:0;font-size:1.1rem;font-weight:700;color:#059669;border:none;background:none;\">On Call Resources</h2>\n    <p style=\"margin:0;font-size:0.75rem;color:#059669;opacity:0.85;\">Schedules and reference materials for on-call coverage</p>\n  </div>\n</div>\n\n<h3 id=\"faculty-call-schedule\">Faculty Call Schedule</h3>\n<div style=\"margin:1.25rem 0;border-radius:10px;overflow:hidden;border:1px solid #e2e8f0;box-shadow:0 1px 4px rgba(0,0,0,0.08);\">\n  <div style=\"padding:0.6rem 0.875rem;background:#f8fafc;border-bottom:1px solid #e2e8f0;display:flex;align-items:center;justify-content:space-between;gap:0.5rem;flex-wrap:wrap;\">\n    <span style=\"font-size:0.8rem;font-weight:600;color:#1e293b;\">📅 Faculty Call Schedule (July 2025 – June 2026)</span>\n    <a href=\"/pdfs/neuro-on-call/call-schedule.xlsx\" download style=\"font-size:0.75rem;color:#2563eb;white-space:nowrap;text-decoration:none;background:#eff6ff;border:1px solid #bfdbfe;border-radius:6px;padding:0.25rem 0.6rem;\">Download XLSX ↗</a>\n  </div>\n  <iframe src=\"/call-schedule/\" class=\"spreadsheet-embed\" width=\"100%\" style=\"height:650px;display:block;border:none;background:#fafafa;\"></iframe>\n</div>\n</section>\n",
  "imageCount": 2,
  "chunkCount": 3,
  "tocCount": 8
}